{
  "Diplomacy": [
    {
      "source": "La Jornada",
      "url": "https://www.jornada.com.mx/2026/05/12/mundo/022n1mun?partner=rss",
      "published_date": "2026-05-12T08:41:32+00:00",
      "category": "Diplomacy",
      "title": "Tehran proposal, “stupid and garbage”; truce, in critical condition"
    },
    {
      "source": "La Jornada",
      "url": "https://www.jornada.com.mx/2026/05/12/mundo/022n2mun?partner=rss",
      "published_date": "2026-05-12T08:41:32+00:00",
      "category": "Diplomacy",
      "title": "Joint work and mutual respect with the US, China maintains"
    },
    {
      "source": "La Jornada",
      "url": "https://www.jornada.com.mx/2026/05/12/economia/016n1eco?partner=rss",
      "published_date": "2026-05-12T08:41:32+00:00",
      "category": "Diplomacy",
      "title": "Faced with increase, Trump seeks gasoline subsidy"
    },
    {
      "source": "La Jornada",
      "url": "https://www.jornada.com.mx/2026/05/12/mundo/018n1mun?partner=rss",
      "published_date": "2026-05-12T08:41:32+00:00",
      "category": "Diplomacy",
      "title": "Given failure towards Cuba, Trump could start something more dangerous"
    },
    {
      "source": "La Jornada",
      "url": "https://www.jornada.com.mx/2026/05/12/mundo/019n2mun?partner=rss",
      "published_date": "2026-05-12T08:41:32+00:00",
      "category": "Diplomacy",
      "title": "There were “very great complicities” in Venezuela during the US operation against Maduro: Guterres"
    },
    {
      "source": "La Jornada",
      "url": "https://www.jornada.com.mx/2026/05/12/mundo/018n3mun?partner=rss",
      "published_date": "2026-05-12T08:41:32+00:00",
      "category": "Diplomacy",
      "title": "US will remove citizenship from spy"
    },
    {
      "source": "La Jornada",
      "url": "https://www.jornada.com.mx/2026/05/12/deportes/a11n2dep?partner=rss",
      "published_date": "2026-05-12T08:41:32+00:00",
      "category": "Diplomacy",
      "title": "They will promote social campaigns for unity and against racism"
    },
    {
      "source": "La Jornada",
      "url": "https://www.jornada.com.mx/2026/05/12/mundo/021n2mun?partner=rss",
      "published_date": "2026-05-12T08:41:32+00:00",
      "category": "Diplomacy",
      "title": "Former Vice President of Ecuador Lenín Moreno is prosecuted for receiving a millionaire bribe"
    },
    {
      "source": "La Jornada",
      "url": "https://www.jornada.com.mx/2026/05/12/mundo/019n1mun?partner=rss",
      "published_date": "2026-05-12T08:41:32+00:00",
      "category": "Diplomacy",
      "title": "Amid growing pressure on Cuba, the UN rules out a military solution"
    },
    {
      "source": "La Jornada",
      "url": "https://www.jornada.com.mx/2026/05/12/opinion/015o1eco?partner=rss",
      "published_date": "2026-05-12T08:41:32+00:00",
      "category": "Diplomacy",
      "title": "Miguel Pineda: Business and companies"
    },
    {
      "source": "La Jornada",
      "url": "https://www.jornada.com.mx/2026/05/12/politica/013a2pol?partner=rss",
      "published_date": "2026-05-12T08:41:32+00:00",
      "category": "Diplomacy",
      "title": "Hallier Arnulfo Morales Dueñas*: Cuba 1960-2026. Parallels of attention"
    },
    {
      "source": "La Jornada",
      "url": "https://www.jornada.com.mx/2026/05/12/mundo/023n3mun?partner=rss",
      "published_date": "2026-05-12T08:41:32+00:00",
      "category": "Diplomacy",
      "title": "Israel violates the ceasefire in Lebanon again; kills 11 in attacks"
    },
    {
      "source": "La Jornada",
      "url": "https://www.jornada.com.mx/2026/05/12/politica/006n2pol?partner=rss",
      "published_date": "2026-05-12T08:41:32+00:00",
      "category": "Diplomacy",
      "title": "Vice Admiral Farías asks Sheinbaum for help again"
    },
    {
      "source": "La Jornada",
      "url": "https://www.jornada.com.mx/2026/05/12/economia/014n2eco?partner=rss",
      "published_date": "2026-05-12T08:41:32+00:00",
      "category": "Diplomacy",
      "title": "New trade agreement between Mexico and EU advances"
    },
    {
      "source": "La Jornada",
      "url": "https://www.jornada.com.mx/2026/05/12/mundo/022n3mun?partner=rss",
      "published_date": "2026-05-12T08:41:32+00:00",
      "category": "Diplomacy",
      "title": "The tycoon's refusal of the Iranian plan raises the price of oil again"
    },
    {
      "source": "La Jornada",
      "url": "https://www.jornada.com.mx/2026/05/12/economia/016n2eco?partner=rss",
      "published_date": "2026-05-12T08:41:32+00:00",
      "category": "Diplomacy",
      "title": "Mexican automobile exports to the US rise 11%"
    },
    {
      "source": "La Jornada",
      "url": "https://www.jornada.com.mx/2026/05/12/mundo/021n1mun?partner=rss",
      "published_date": "2026-05-12T08:41:32+00:00",
      "category": "Diplomacy",
      "title": "Raids leave migrants and Americans without jobs"
    },
    {
      "source": "La Jornada",
      "url": "https://www.jornada.com.mx/2026/05/12/mundo/020n2mun?partner=rss",
      "published_date": "2026-05-12T08:41:32+00:00",
      "category": "Diplomacy",
      "title": "Activists install a temporary library of the Epstein case in NY"
    },
    {
      "source": "La Jornada",
      "url": "https://www.jornada.com.mx/2026/05/12/mundo/019n3mun?partner=rss",
      "published_date": "2026-05-12T08:41:32+00:00",
      "category": "Diplomacy",
      "title": "Ship sets sail for Havana with more Mexican aid"
    },
    {
      "source": "La Jornada",
      "url": "https://www.jornada.com.mx/2026/05/12/economia/015n1eco?partner=rss",
      "published_date": "2026-05-12T08:41:32+00:00",
      "category": "Diplomacy",
      "title": "Payments to Mexican migrants grow 62% in the US"
    }
  ],
  "Military": [
    {
      "source": "La Jornada",
      "url": "https://www.jornada.com.mx/2026/05/12/politica/005n2pol?partner=rss",
      "published_date": "2026-05-12T08:41:32+00:00",
      "category": "Military",
      "title": "PAN calls for impeachment against the Morenista"
    },
    {
      "source": "La Jornada",
      "url": "https://www.jornada.com.mx/2026/05/12/mundo/020n1mun?partner=rss",
      "published_date": "2026-05-12T08:41:32+00:00",
      "category": "Military",
      "title": "Trials resume for perpetrators of deaths and disappearances in the Argentine dictatorship"
    },
    {
      "source": "La Jornada",
      "url": "https://www.jornada.com.mx/2026/05/12/estados/024n1est?partner=rss",
      "published_date": "2026-05-12T08:41:32+00:00",
      "category": "Military",
      "title": "Los Ardillos killed 3 members of Cipog-EZ and two disappeared"
    },
    {
      "source": "La Jornada",
      "url": "https://www.jornada.com.mx/2026/05/12/politica/005n3pol?partner=rss",
      "published_date": "2026-05-12T08:41:32+00:00",
      "category": "Military",
      "title": "Los Chapitos analyze surrendering and collaborating with the neighboring country to the north"
    },
    {
      "source": "La Jornada",
      "url": "https://www.jornada.com.mx/2026/05/12/espectaculos/a07n1esp?partner=rss",
      "published_date": "2026-05-12T08:41:32+00:00",
      "category": "Military",
      "title": "Together with Majo Aguilar and Junior H, Sheinbaum launches the second edition of México canta"
    },
    {
      "source": "La Jornada",
      "url": "https://www.jornada.com.mx/2026/05/12/estados/025n4est?partner=rss",
      "published_date": "2026-05-12T08:41:32+00:00",
      "category": "Military",
      "title": "Tamazula teachers ask to be evacuated due to violence"
    },
    {
      "source": "La Jornada",
      "url": "https://www.jornada.com.mx/2026/05/12/politica/013a1pol?partner=rss",
      "published_date": "2026-05-12T08:41:32+00:00",
      "category": "Military",
      "title": "Luis Hernández Navarro: Chilapa, the murderous saga of Los Ardillos"
    },
    {
      "source": "La Jornada",
      "url": "https://www.jornada.com.mx/2026/05/12/capital/029n2cap?partner=rss",
      "published_date": "2026-05-12T08:41:32+00:00",
      "category": "Military",
      "title": "Cyclists demand greater security and control due to the works in Tlalpan"
    },
    {
      "source": "La Jornada",
      "url": "https://www.jornada.com.mx/2026/05/12/politica/005n1pol?partner=rss",
      "published_date": "2026-05-12T08:41:32+00:00",
      "category": "Military",
      "title": "The President rules out that the US removes Rocha Moya"
    },
    {
      "source": "La Jornada",
      "url": "https://www.jornada.com.mx/2026/05/12/capital/028n2cap?partner=rss",
      "published_date": "2026-05-12T08:41:32+00:00",
      "category": "Military",
      "title": "The alleged perpetrators of the shooting at the Mother's Day party are captured"
    },
    {
      "source": "La Jornada",
      "url": "https://www.jornada.com.mx/2026/05/12/politica/004n1pol?partner=rss",
      "published_date": "2026-05-12T08:41:32+00:00",
      "category": "Military",
      "title": "IACHR: Mexico, in serious crisis; denounces state collusion in disappearances"
    },
    {
      "source": "La Jornada",
      "url": "https://www.jornada.com.mx/2026/05/12/politica/007n2pol?partner=rss",
      "published_date": "2026-05-12T08:41:32+00:00",
      "category": "Military",
      "title": "Governor of BC reinforces surveillance and connectivity in Valle de Guadalupe"
    },
    {
      "source": "La Jornada",
      "url": "https://www.jornada.com.mx/2026/05/12/politica/004n2pol?partner=rss",
      "published_date": "2026-05-12T08:41:32+00:00",
      "category": "Military",
      "title": "“If organized crime does not kill us, depression destroys us”: search engine"
    },
    {
      "source": "La Jornada",
      "url": "https://www.jornada.com.mx/2026/05/12/estados/024n3est?partner=rss",
      "published_date": "2026-05-12T08:41:32+00:00",
      "category": "Military",
      "title": "The presence of the GN in the area will be reinforced: Sheinbaum"
    },
    {
      "source": "La Jornada",
      "url": "https://www.jornada.com.mx/2026/05/12/espectaculos/a08n1esp?partner=rss",
      "published_date": "2026-05-12T08:41:32+00:00",
      "category": "Military",
      "title": "BTS followers throw a party in “zone A (outside)”"
    },
    {
      "source": "La Jornada",
      "url": "https://www.jornada.com.mx/2026/05/12/politica/003n2pol?partner=rss",
      "published_date": "2026-05-12T08:41:32+00:00",
      "category": "Military",
      "title": "Delgado, the only one who did not go to the military party"
    },
    {
      "source": "La Jornada",
      "url": "https://www.jornada.com.mx/2026/05/11/estados/025n1est?partner=rss",
      "published_date": "2026-05-11T08:27:27+00:00",
      "category": "Military",
      "title": "Caravan of dozens of displaced people from Durango attacked in Chihuahua"
    },
    {
      "source": "La Jornada",
      "url": "https://www.jornada.com.mx/2026/05/11/estados/026n3est?partner=rss",
      "published_date": "2026-05-11T08:27:27+00:00",
      "category": "Military",
      "title": "BC: Roxana N is linked to proceedings for the death of her son"
    },
    {
      "source": "La Jornada",
      "url": "https://www.jornada.com.mx/2026/05/11/sociedad/031n3soc?partner=rss",
      "published_date": "2026-05-11T08:27:27+00:00",
      "category": "Military",
      "title": "3 former FGR agents are sentenced for extortion in Edomex"
    },
    {
      "source": "La Jornada",
      "url": "https://www.jornada.com.mx/2026/05/11/estados/026n2est?partner=rss",
      "published_date": "2026-05-11T08:27:27+00:00",
      "category": "Military",
      "title": "Uncertain, the future of Mahahual, after the Court's approval of the shipping company's aquatic project"
    }
  ],
  "Energy": [
    {
      "source": "La Jornada",
      "url": "https://www.jornada.com.mx/2026/05/12/economia/016n3eco?partner=rss",
      "published_date": "2026-05-12T08:41:32+00:00",
      "category": "Energy",
      "title": "Only 31% of gas stations have respected federal agreement on diesel prices"
    },
    {
      "source": "La Jornada",
      "url": "https://www.jornada.com.mx/2026/05/12/economia/014n3eco?partner=rss",
      "published_date": "2026-05-12T08:41:32+00:00",
      "category": "Energy",
      "title": "Government policies contribute to the bean crisis: GCMA"
    },
    {
      "source": "La Jornada",
      "url": "https://www.jornada.com.mx/2026/05/12/politica/006n1pol?partner=rss",
      "published_date": "2026-05-12T08:41:32+00:00",
      "category": "Energy",
      "title": "Huachitúnel found in Pemex facilities attached to a house in NL"
    },
    {
      "source": "La Jornada",
      "url": "https://www.jornada.com.mx/2026/05/11/opinion/012o1pol?partner=rss",
      "published_date": "2026-05-11T08:27:27+00:00",
      "category": "Energy",
      "title": "Ortiz Tejeda: We are no longer the same"
    },
    {
      "source": "La Jornada",
      "url": "https://www.jornada.com.mx/2026/05/11/politica/010a1pol?partner=rss",
      "published_date": "2026-05-11T08:27:27+00:00",
      "category": "Energy",
      "title": "José Murat: Ayuso and the spirit of vassalage"
    },
    {
      "source": "La Jornada",
      "url": "https://www.jornada.com.mx/2026/05/11/economia/017n2eco?partner=rss",
      "published_date": "2026-05-11T08:27:27+00:00",
      "category": "Energy",
      "title": "Production at the Dos Bocas refinery fell 12.84% in March"
    },
    {
      "source": "La Jornada",
      "url": "https://www.jornada.com.mx/2026/05/11/opinion/018o1eco?partner=rss",
      "published_date": "2026-05-11T08:27:27+00:00",
      "category": "Energy",
      "title": "Carlos Fernández-Vega: Mexico SA"
    },
    {
      "source": "La Jornada",
      "url": "https://www.jornada.com.mx/2026/05/11/economia/017n1eco?partner=rss",
      "published_date": "2026-05-11T08:27:27+00:00",
      "category": "Energy",
      "title": "Fitch: oil will be 24% more expensive due to long closure of Hormuz"
    },
    {
      "source": "La Jornada",
      "url": "https://www.jornada.com.mx/2026/05/10/estados/022n1est?partner=rss",
      "published_date": "2026-05-10T10:54:13+00:00",
      "category": "Energy",
      "title": "3 American bison calves are born in El Santuario Reserve, in Coahuila"
    },
    {
      "source": "La Jornada",
      "url": "https://www.jornada.com.mx/2026/05/09/politica/007n1pol?partner=rss",
      "published_date": "2026-05-09T10:53:16+00:00",
      "category": "Energy",
      "title": "Sheinbaum inaugurates aqueduct for Seri community in Sonora"
    },
    {
      "source": "La Jornada",
      "url": "https://www.jornada.com.mx/2026/05/09/estados/022n2est?partner=rss",
      "published_date": "2026-05-09T10:53:16+00:00",
      "category": "Energy",
      "title": "Activities restart at the Tabasco Fair; They provide financial support to 200 affected people"
    },
    {
      "source": "La Jornada",
      "url": "https://www.jornada.com.mx/2026/05/09/deportes/a27n2dep?partner=rss",
      "published_date": "2026-05-09T10:53:16+00:00",
      "category": "Energy",
      "title": "Mexican Vodnik achieves victory with the Rockies in the MLB"
    },
    {
      "source": "La Jornada",
      "url": "https://www.jornada.com.mx/2026/05/09/politica/006n1pol?partner=rss",
      "published_date": "2026-05-09T10:53:16+00:00",
      "category": "Energy",
      "title": "The FGR is made with a Lozoya residence valued at 51 million pesos"
    },
    {
      "source": "La Jornada",
      "url": "https://www.jornada.com.mx/2026/05/09/espectaculos/a08n1esp?partner=rss",
      "published_date": "2026-05-09T10:53:16+00:00",
      "category": "Energy",
      "title": "Coilguns release Peace Trader"
    },
    {
      "source": "La Jornada",
      "url": "https://www.jornada.com.mx/2026/05/08/estados/025n1est?partner=rss",
      "published_date": "2026-05-08T10:28:21+00:00",
      "category": "Energy",
      "title": "Bean producers break into the session of the Zacatecas Congress"
    },
    {
      "source": "La Jornada",
      "url": "https://www.jornada.com.mx/2026/05/08/politica/007n1pol?partner=rss",
      "published_date": "2026-05-08T10:28:21+00:00",
      "category": "Energy",
      "title": "Without evidence of criminal leagues, the INE does not investigate candidates: Taddei"
    },
    {
      "source": "La Jornada",
      "url": "https://www.jornada.com.mx/2026/05/08/economia/015n2eco?partner=rss",
      "published_date": "2026-05-08T10:28:21+00:00",
      "category": "Energy",
      "title": "140 thousand million pesos will be allocated to the national gas pipeline network"
    },
    {
      "source": "La Jornada",
      "url": "https://www.jornada.com.mx/2026/05/08/politica/013a2pol?partner=rss",
      "published_date": "2026-05-08T10:28:21+00:00",
      "category": "Energy",
      "title": "Simón Vargas Aguilar*: Teachers in Mexico, they deserve more than just applause"
    },
    {
      "source": "La Jornada",
      "url": "https://www.jornada.com.mx/2026/05/08/economia/014n2eco?partner=rss",
      "published_date": "2026-05-08T10:28:21+00:00",
      "category": "Energy",
      "title": "Sheinbaum: without containment measures, the increase would be around 10%"
    },
    {
      "source": "La Jornada",
      "url": "https://www.jornada.com.mx/2026/05/08/politica/012a2pol?partner=rss",
      "published_date": "2026-05-08T10:28:21+00:00",
      "category": "Energy",
      "title": "Juan Carlos Cruz Barrientos: Costa Rica: the interregnum and the dispute for common sense"
    }
  ],
  "Economy": [
    {
      "source": "La Jornada",
      "url": "https://www.jornada.com.mx/2026/05/12/economia/015n3eco?partner=rss",
      "published_date": "2026-05-12T08:41:32+00:00",
      "category": "Economy",
      "title": "Development banks receive 345 strategic projects"
    },
    {
      "source": "La Jornada",
      "url": "https://www.jornada.com.mx/2026/05/12/economia/015n2eco?partner=rss",
      "published_date": "2026-05-12T08:41:32+00:00",
      "category": "Economy",
      "title": "Ready, ambitious infrastructure plan: SHCP"
    },
    {
      "source": "La Jornada",
      "url": "https://www.jornada.com.mx/2026/05/12/economia/014n1eco?partner=rss",
      "published_date": "2026-05-12T08:41:32+00:00",
      "category": "Economy",
      "title": "Cost of the basic basket rises almost twice as much as inflation"
    },
    {
      "source": "La Jornada",
      "url": "https://www.jornada.com.mx/2026/05/12/economia/017n2eco?partner=rss",
      "published_date": "2026-05-12T08:41:32+00:00",
      "category": "Economy",
      "title": "Insurers must move towards long-term non-slavery policies, says expert"
    },
    {
      "source": "La Jornada",
      "url": "https://www.jornada.com.mx/2026/05/12/politica/010n1pol?partner=rss",
      "published_date": "2026-05-12T08:41:32+00:00",
      "category": "Economy",
      "title": "Nine former AHMSA workers arrested for blocking the road"
    },
    {
      "source": "La Jornada",
      "url": "https://www.jornada.com.mx/2026/05/12/opinion/028o1cap?partner=rss",
      "published_date": "2026-05-12T08:41:32+00:00",
      "category": "Economy",
      "title": "Miguel Ángel Velázquez: Lost City"
    },
    {
      "source": "La Jornada",
      "url": "https://www.jornada.com.mx/2026/05/12/capital/029n3cap?partner=rss",
      "published_date": "2026-05-12T08:41:32+00:00",
      "category": "Economy",
      "title": "Leader reproaches small merchants for exclusion from football festival"
    },
    {
      "source": "La Jornada",
      "url": "https://www.jornada.com.mx/2026/05/12/sociedad/031n1soc?partner=rss",
      "published_date": "2026-05-12T08:41:32+00:00",
      "category": "Economy",
      "title": "They denounce that legal opacity slows down the production of drugs"
    },
    {
      "source": "La Jornada",
      "url": "https://www.jornada.com.mx/2026/05/11/economia/016a1eco?partner=rss",
      "published_date": "2026-05-11T08:27:27+00:00",
      "category": "Economy",
      "title": "León Bendesky: The light post"
    },
    {
      "source": "La Jornada",
      "url": "https://www.jornada.com.mx/2026/05/11/economia/016n1eco?partner=rss",
      "published_date": "2026-05-11T08:27:27+00:00",
      "category": "Economy",
      "title": "Banks obtained profits of $80 billion during the first quarter of this year"
    },
    {
      "source": "La Jornada",
      "url": "https://www.jornada.com.mx/2026/05/11/economia/015n2eco?partner=rss",
      "published_date": "2026-05-11T08:27:27+00:00",
      "category": "Economy",
      "title": "Mexico and Canada agree to pharmaceutical cooperation"
    },
    {
      "source": "La Jornada",
      "url": "https://www.jornada.com.mx/2026/05/11/politica/009n3pol?partner=rss",
      "published_date": "2026-05-11T08:27:27+00:00",
      "category": "Economy",
      "title": "Sheinbaum and Durazo provide support to women in Sonora"
    },
    {
      "source": "La Jornada",
      "url": "https://www.jornada.com.mx/2026/05/11/economia/016n3eco?partner=rss",
      "published_date": "2026-05-11T08:27:27+00:00",
      "category": "Economy",
      "title": "Aramco succeeds in avoiding Hormuz"
    },
    {
      "source": "La Jornada",
      "url": "https://www.jornada.com.mx/2026/05/11/capital/029n1cap?partner=rss",
      "published_date": "2026-05-11T08:27:27+00:00",
      "category": "Economy",
      "title": "Shops, bars and restaurants were the most requested places on May 10"
    },
    {
      "source": "La Jornada",
      "url": "https://www.jornada.com.mx/2026/05/11/economia/015n1eco?partner=rss",
      "published_date": "2026-05-11T08:27:27+00:00",
      "category": "Economy",
      "title": "Computers make up for the drop in car exports to the US"
    },
    {
      "source": "La Jornada",
      "url": "https://www.jornada.com.mx/2026/05/11/deportes/a12n1dep?partner=rss",
      "published_date": "2026-05-11T08:27:27+00:00",
      "category": "Economy",
      "title": "Geopolitical tension and criticism of FIFA one month before the World Cup"
    },
    {
      "source": "La Jornada",
      "url": "https://www.jornada.com.mx/2026/05/11/politica/009n1pol?partner=rss",
      "published_date": "2026-05-11T08:27:27+00:00",
      "category": "Economy",
      "title": "States stopped spending 21,409 million pesos on health in 2025: report"
    },
    {
      "source": "La Jornada",
      "url": "https://www.jornada.com.mx/2026/05/11/opinion/017o1eco?partner=rss",
      "published_date": "2026-05-11T08:27:27+00:00",
      "category": "Economy",
      "title": "David Márquez Ayala: Economic report"
    },
    {
      "source": "La Jornada",
      "url": "https://www.jornada.com.mx/2026/05/11/opinion/a10o1dep?partner=rss",
      "published_date": "2026-05-11T08:27:27+00:00",
      "category": "Economy",
      "title": "Marlene Santos Alejo: Balance of the day"
    },
    {
      "source": "La Jornada",
      "url": "https://www.jornada.com.mx/2026/05/10/cultura/a12n1vox?partner=rss",
      "published_date": "2026-05-10T10:54:13+00:00",
      "category": "Economy",
      "title": "Books"
    }
  ],
  "Local Events": [
    {
      "source": "La Jornada",
      "url": "https://www.jornada.com.mx/2026/05/12/opinion/002a1edi?partner=rss",
      "published_date": "2026-05-12T08:41:32+00:00",
      "category": "Local Events",
      "title": "Editorial: School cycle: the virtue of rectifying"
    },
    {
      "source": "La Jornada",
      "url": "https://www.jornada.com.mx/2026/05/12/estados/025n1est?partner=rss",
      "published_date": "2026-05-12T08:41:32+00:00",
      "category": "Local Events",
      "title": "Governments of Chilapa, Guerrero and federal, ignoring the criminal offensive: lawyer"
    },
    {
      "source": "La Jornada",
      "url": "https://www.jornada.com.mx/2026/05/12/estados/026n3est?partner=rss",
      "published_date": "2026-05-12T08:41:32+00:00",
      "category": "Local Events",
      "title": "In Teopisca and San Cristóbal, rejection of highway construction increases"
    },
    {
      "source": "La Jornada",
      "url": "https://www.jornada.com.mx/2026/05/12/politica/007n1pol?partner=rss",
      "published_date": "2026-05-12T08:41:32+00:00",
      "category": "Local Events",
      "title": "CNTE-Chiapas presents demands to Sheinbaum in the National Palace"
    },
    {
      "source": "La Jornada",
      "url": "https://www.jornada.com.mx/2026/05/12/opinion/006o1eco?partner=rss",
      "published_date": "2026-05-12T08:41:32+00:00",
      "category": "Local Events",
      "title": "Enrique Galván Ochoa: Money"
    },
    {
      "source": "La Jornada",
      "url": "https://www.jornada.com.mx/2026/05/12/capital/027n1cap?partner=rss",
      "published_date": "2026-05-12T08:41:32+00:00",
      "category": "Local Events",
      "title": "300 cases of property dispossession remain open; 174 have been resolved: Cravioto"
    },
    {
      "source": "La Jornada",
      "url": "https://www.jornada.com.mx/2026/05/12/estados/026n2est?partner=rss",
      "published_date": "2026-05-12T08:41:32+00:00",
      "category": "Local Events",
      "title": "Tonanitla ejidatarios block access to the AIFA due to border conflict with Tecámac"
    },
    {
      "source": "La Jornada",
      "url": "https://www.jornada.com.mx/2026/05/12/politica/012a1pol?partner=rss",
      "published_date": "2026-05-12T08:41:32+00:00",
      "category": "Local Events",
      "title": "Pedro Salmerón Sanginés: Hernán Cortés again"
    },
    {
      "source": "La Jornada",
      "url": "https://www.jornada.com.mx/2026/05/12/capital/029n1cap?partner=rss",
      "published_date": "2026-05-12T08:41:32+00:00",
      "category": "Local Events",
      "title": "The World Cup gives air to Xochimilco artisans; They make 500 thousand noisemakers"
    },
    {
      "source": "La Jornada",
      "url": "https://www.jornada.com.mx/2026/05/12/politica/006n3pol?partner=rss",
      "published_date": "2026-05-12T08:41:32+00:00",
      "category": "Local Events",
      "title": "Blow to hydrocarbon theft in Nuevo León"
    },
    {
      "source": "La Jornada",
      "url": "https://www.jornada.com.mx/2026/05/12/politica/012a2pol?partner=rss",
      "published_date": "2026-05-12T08:41:32+00:00",
      "category": "Local Events",
      "title": "Víctor M. Quintana S.: We look for them because we love them!"
    },
    {
      "source": "La Jornada",
      "url": "https://www.jornada.com.mx/2026/05/12/estados/026n1est?partner=rss",
      "published_date": "2026-05-12T08:41:32+00:00",
      "category": "Local Events",
      "title": "Thousands demand the dismissal of Zacatecas officials, after repression on the march"
    },
    {
      "source": "La Jornada",
      "url": "https://www.jornada.com.mx/2026/05/12/politica/011n1pol?partner=rss",
      "published_date": "2026-05-12T08:41:32+00:00",
      "category": "Local Events",
      "title": "Leader of the Northeast cartel falls in NL linked to ship with huachicol"
    },
    {
      "source": "La Jornada",
      "url": "https://www.jornada.com.mx/2026/05/12/estados/025n3est?partner=rss",
      "published_date": "2026-05-12T08:41:32+00:00",
      "category": "Local Events",
      "title": "Morenoistas propose a plan to protect people expelled from their communities"
    },
    {
      "source": "La Jornada",
      "url": "https://www.jornada.com.mx/2026/05/12/capital/028n1cap?partner=rss",
      "published_date": "2026-05-12T08:41:32+00:00",
      "category": "Local Events",
      "title": "Heavy rain last night left 18 puddles and 10 fallen trees"
    },
    {
      "source": "La Jornada",
      "url": "https://www.jornada.com.mx/2026/05/12/politica/009n1pol?partner=rss",
      "published_date": "2026-05-12T08:41:32+00:00",
      "category": "Local Events",
      "title": "The SEP backs down; Social pressure pulls plan to bring forward the end of courses"
    },
    {
      "source": "La Jornada",
      "url": "https://www.jornada.com.mx/2026/05/12/capital/027n2cap?partner=rss",
      "published_date": "2026-05-12T08:41:32+00:00",
      "category": "Local Events",
      "title": "With 17 convoys of recent technology, the government inaugurates the renewed Light Train"
    },
    {
      "source": "La Jornada",
      "url": "https://www.jornada.com.mx/2026/05/12/estados/024n2est?partner=rss",
      "published_date": "2026-05-12T08:41:32+00:00",
      "category": "Local Events",
      "title": "CNI calls for a global action to support the indigenous peoples of the Baja Mountain"
    },
    {
      "source": "La Jornada",
      "url": "https://www.jornada.com.mx/2026/05/12/estados/025n2est?partner=rss",
      "published_date": "2026-05-12T08:41:32+00:00",
      "category": "Local Events",
      "title": "Residents of Tula and Alcozacán plead for help for displaced families"
    },
    {
      "source": "La Jornada",
      "url": "https://www.jornada.com.mx/2026/05/12/deportes/a10n1dep?partner=rss",
      "published_date": "2026-05-12T08:41:32+00:00",
      "category": "Local Events",
      "title": "SSC will deploy mega security operation throughout CDMX"
    }
  ]
}